vsutillib/sql/__init__.py
vsutillib/sql/classes/SqlDb.py
vsutillib/sql/classes/__init__.py
vsutillib_sql-1.6.2.dist-info/AUTHORS
vsutillib_sql-1.6.2.dist-info/LICENSE.txt
vsutillib_sql-1.6.2.dist-info/METADATA
vsutillib_sql-1.6.2.dist-info/WHEEL
vsutillib_sql-1.6.2.dist-info/top_level.txt
vsutillib_sql-1.6.2.dist-info/RECORD
